{
  "roads": [
    {
      "id": 1,
      "x": 80,
      "y": 120,
      "w": 600,
      "h": 36,
      "type": "big"
    },
    {
      "id": 2,
      "x": 360,
      "y": 80,
      "w": 36,
      "h": 380,
      "type": "big"
    },
    {
      "id": 3,
      "x": 120,
      "y": 320,
      "w": 520,
      "h": 28,
      "type": "big"
    }
  ],
  "hubs": [
    {
      "id": 1,
      "x": 100,
      "y": 138,
      "name": "Home",
      "rate": 6
    },
    {
      "id": 2,
      "x": 420,
      "y": 138,
      "name": "Mall",
      "rate": 4
    },
    {
      "id": 3,
      "x": 380,
      "y": 360,
      "name": "Office",
      "rate": 2
    }
  ],
  "lights": [
    {
      "id": 1,
      "x": 360,
      "y": 138,
      "green": 6,
      "red": 4
    }
  ],
  "symbols": [
    {
      "id": 1,
      "x": 260,
      "y": 138,
      "type": "slow"
    }
  ]
}